setup.py
excel21jsonapi/__init__.py
excel21jsonapi.egg-info/PKG-INFO
excel21jsonapi.egg-info/SOURCES.txt
excel21jsonapi.egg-info/dependency_links.txt
excel21jsonapi.egg-info/not-zip-safe
excel21jsonapi.egg-info/top_level.txt