Metadata-Version: 1.0
Name: excel21jsonapi
Version: 0.1
Summary: Convert excel into json response
Home-page: https://github.com/tonewbeginning/excel21jsonapi
Author: RS
Author-email: tonewbeginning@gmail.com
License: MIT
Platform: UNKNOWN
